ao_ann/__init__.py
ao_ann/ann.py
ao_ann/dataset.py
ao_ann/loss.py
ao_ann/model.py
ao_ann/utils.py
ao_ann-0.1.6.dist-info/METADATA
ao_ann-0.1.6.dist-info/WHEEL
ao_ann-0.1.6.dist-info/top_level.txt
ao_ann-0.1.6.dist-info/RECORD
