Metadata-Version: 2.2
Name: ao_ann
Version: 0.1.6
Summary: American Options Pricing ANN
Author-email: Mustafif Khan <me@mustafif.com>
Maintainer-email: Mustafif Khan <me@mustafif.com>
Project-URL: Repository, https://github.com/Mustafif/AO_ANN
Project-URL: Issues, https://github.com/Mustafif/AO_ANN/issues
Classifier: License :: OSI Approved :: MIT License
Classifier: Programming Language :: Python :: 3
Classifier: Operating System :: OS Independent
Requires-Python: >=3.13
Requires-Dist: matplotlib>=3.10.1
Requires-Dist: numpy>=2.2.3
Requires-Dist: pandas>=2.2.3
Requires-Dist: scikit-learn>=1.6.1
Requires-Dist: sphinx>=8.2.3
Requires-Dist: torch>=2.6.0
